{
  "status": "IDLE",
  "prepFlag": "P",
  "wind": {
    "direction": 0.0,
    "speed": 12.0
  },
  "course": {
    "marks": [],
    "courseBoundary": [],
    "settings": {
      "showMarkZones": true,
      "markZoneMultiplier": 3.0
    }
  },
  "currentProcedure": {
    "id": "custom-1771923253430",
    "nodes": [
      {
        "id": "0",
        "type": "state",
        "data": {
          "label": "Idle",
          "flags": [],
          "duration": 0.0,
          "sound": "NONE",
          "soundOnRemove": "NONE",
          "waitForUserTrigger": false,
          "postTriggerDuration": 0.0,
          "postTriggerFlags": []
        },
        "position": {
          "x": 250.7401453957997,
          "y": 50
        }
      },
      {
        "id": "1",
        "type": "state",
        "data": {
          "label": "Warning Signal",
          "flags": [
            "CLASS"
          ],
          "duration": 60.0,
          "sound": "NONE",
          "soundOnRemove": "NONE",
          "waitForUserTrigger": false,
          "postTriggerDuration": 0.0,
          "postTriggerFlags": []
        },
        "position": {
          "x": 250,
          "y": 200
        }
      },
      {
        "id": "2",
        "type": "state",
        "data": {
          "label": "Preparatory Signal",
          "flags": [
            "CLASS",
            "P"
          ],
          "duration": 180.0,
          "sound": "NONE",
          "soundOnRemove": "NONE",
          "waitForUserTrigger": false,
          "postTriggerDuration": 0.0,
          "postTriggerFlags": []
        },
        "position": {
          "x": 250,
          "y": 350
        }
      },
      {
        "id": "3",
        "type": "state",
        "data": {
          "label": "One-Minute",
          "flags": [
            "CLASS"
          ],
          "duration": 60.0,
          "sound": "NONE",
          "soundOnRemove": "NONE",
          "waitForUserTrigger": false,
          "postTriggerDuration": 0.0,
          "postTriggerFlags": []
        },
        "position": {
          "x": 250,
          "y": 500
        }
      },
      {
        "id": "4",
        "type": "state",
        "data": {
          "label": "Start",
          "flags": [],
          "duration": 0.0,
          "sound": "NONE",
          "soundOnRemove": "NONE",
          "waitForUserTrigger": false,
          "postTriggerDuration": 0.0,
          "postTriggerFlags": []
        },
        "position": {
          "x": 250,
          "y": 650
        }
      },
      {
        "id": "5",
        "type": "state",
        "data": {
          "label": "Racing",
          "flags": [],
          "duration": 3600.0,
          "sound": "NONE",
          "soundOnRemove": "NONE",
          "waitForUserTrigger": false,
          "postTriggerDuration": 0.0,
          "postTriggerFlags": []
        },
        "position": {
          "x": 250,
          "y": 800
        }
      }
    ],
    "edges": [
      {
        "id": "e0-1",
        "source": "0",
        "target": "1"
      },
      {
        "id": "e1-2",
        "source": "1",
        "target": "2"
      },
      {
        "id": "e2-3",
        "source": "2",
        "target": "3"
      },
      {
        "id": "e3-4",
        "source": "3",
        "target": "4"
      },
      {
        "id": "e4-5",
        "source": "4",
        "target": "5"
      }
    ],
    "autoRestart": false
  },
  "defaultLocation": {
    "lat": 60.1699,
    "lon": 24.9384,
    "zoom": 17.0
  },
  "waitingForTrigger": false,
  "isPostTrigger": false,
  "timeLimits": {},
  "ocsBoats": [],
  "boats": {},
  "penalties": [],
  "logs": [
    {
      "id": "log-1771922901297",
      "timestamp": 1771922901297,
      "category": "COURSE",
      "source": "Director",
      "message": "Course layout updated",
      "isActive": false
    },
    {
      "id": "log-1771922901298",
      "timestamp": 1771922901298,
      "category": "COURSE",
      "source": "Director",
      "message": "Course layout updated",
      "isActive": false
    },
    {
      "id": "log-1771922901300",
      "timestamp": 1771922901300,
      "category": "COURSE",
      "source": "Director",
      "message": "Course layout updated",
      "isActive": false
    },
    {
      "id": "log-1771922901301",
      "timestamp": 1771922901301,
      "category": "COURSE",
      "source": "Director",
      "message": "Course layout updated",
      "isActive": false
    },
    {
      "id": "log-1771923052797",
      "timestamp": 1771923052797,
      "category": "COURSE",
      "source": "Director",
      "message": "Course layout updated",
      "isActive": false
    },
    {
      "id": "log-1771923054246",
      "timestamp": 1771923054246,
      "category": "COURSE",
      "source": "Director",
      "message": "Course layout updated",
      "isActive": false
    },
    {
      "id": "log-1771923055779",
      "timestamp": 1771923055779,
      "category": "COURSE",
      "source": "Director",
      "message": "Course layout updated",
      "isActive": false
    },
    {
      "id": "log-1771923057613",
      "timestamp": 1771923057613,
      "category": "COURSE",
      "source": "Director",
      "message": "Course layout updated",
      "isActive": false
    },
    {
      "id": "log-1771923078797",
      "timestamp": 1771923078797,
      "category": "COURSE",
      "source": "Director",
      "message": "Course layout updated",
      "isActive": false
    },
    {
      "id": "log-1771923086115",
      "timestamp": 1771923086115,
      "category": "COURSE",
      "source": "Director",
      "message": "Course layout updated",
      "isActive": false
    },
    {
      "id": "log-1771923089363",
      "timestamp": 1771923089363,
      "category": "COURSE",
      "source": "Director",
      "message": "Course layout updated",
      "isActive": false
    },
    {
      "id": "log-1771923091431",
      "timestamp": 1771923091431,
      "category": "COURSE",
      "source": "Director",
      "message": "Course layout updated",
      "isActive": false
    },
    {
      "id": "log-1771923101299",
      "timestamp": 1771923101299,
      "category": "COURSE",
      "source": "Director",
      "message": "Course layout updated",
      "isActive": false
    },
    {
      "id": "log-1771923108649",
      "timestamp": 1771923108649,
      "category": "COURSE",
      "source": "Director",
      "message": "Course layout updated",
      "isActive": false
    },
    {
      "id": "log-1771923122131",
      "timestamp": 1771923122131,
      "category": "COURSE",
      "source": "Director",
      "message": "Course layout updated",
      "isActive": false
    },
    {
      "id": "log-1771923126281",
      "timestamp": 1771923126281,
      "category": "COURSE",
      "source": "Director",
      "message": "Course layout updated",
      "isActive": false
    },
    {
      "id": "log-1771923129047",
      "timestamp": 1771923129047,
      "category": "COURSE",
      "source": "Director",
      "message": "Course layout updated",
      "isActive": false
    },
    {
      "id": "log-1771923131616",
      "timestamp": 1771923131616,
      "category": "COURSE",
      "source": "Director",
      "message": "Course layout updated",
      "isActive": false
    },
    {
      "id": "log-1771923133682",
      "timestamp": 1771923133682,
      "category": "COURSE",
      "source": "Director",
      "message": "Course layout updated",
      "isActive": false
    },
    {
      "id": "log-1771923137982",
      "timestamp": 1771923137982,
      "category": "COURSE",
      "source": "Director",
      "message": "Course layout updated",
      "isActive": false
    },
    {
      "id": "log-1771923143865",
      "timestamp": 1771923143865,
      "category": "COURSE",
      "source": "Director",
      "message": "Course layout updated",
      "isActive": false
    },
    {
      "id": "log-1771923146247",
      "timestamp": 1771923146247,
      "category": "COURSE",
      "source": "Director",
      "message": "Course layout updated",
      "isActive": false
    },
    {
      "id": "log-1771923149582",
      "timestamp": 1771923149582,
      "category": "COURSE",
      "source": "Director",
      "message": "Course layout updated",
      "isActive": false
    },
    {
      "id": "log-1771923151998",
      "timestamp": 1771923151998,
      "category": "COURSE",
      "source": "Director",
      "message": "Course layout updated",
      "isActive": false
    },
    {
      "id": "log-1771923158882",
      "timestamp": 1771923158882,
      "category": "COURSE",
      "source": "Director",
      "message": "Course layout updated",
      "isActive": false
    },
    {
      "id": "log-1771923160699",
      "timestamp": 1771923160699,
      "category": "COURSE",
      "source": "Director",
      "message": "Course layout updated",
      "isActive": false
    },
    {
      "id": "log-1771923164198",
      "timestamp": 1771923164198,
      "category": "COURSE",
      "source": "Director",
      "message": "Course layout updated",
      "isActive": false
    },
    {
      "id": "log-1771923165383",
      "timestamp": 1771923165383,
      "category": "COURSE",
      "source": "Director",
      "message": "Course layout updated",
      "isActive": false
    },
    {
      "id": "log-1771923174448",
      "timestamp": 1771923174448,
      "category": "COURSE",
      "source": "Director",
      "message": "Course layout updated",
      "isActive": false
    },
    {
      "id": "log-1771923178281",
      "timestamp": 1771923178281,
      "category": "COURSE",
      "source": "Director",
      "message": "Course layout updated",
      "isActive": false
    },
    {
      "id": "log-1771923181715",
      "timestamp": 1771923181715,
      "category": "COURSE",
      "source": "Director",
      "message": "Course layout updated",
      "isActive": false
    },
    {
      "id": "log-1771923192915",
      "timestamp": 1771923192915,
      "category": "COURSE",
      "source": "Director",
      "message": "Course layout updated",
      "isActive": false
    },
    {
      "id": "log-1771923198582",
      "timestamp": 1771923198582,
      "category": "COURSE",
      "source": "Director",
      "message": "Course layout updated",
      "isActive": false
    },
    {
      "id": "log-1771923201883",
      "timestamp": 1771923201883,
      "category": "COURSE",
      "source": "Director",
      "message": "Course layout updated",
      "isActive": false
    }
  ],
  "fleetHistory": {},
  "teams": {},
  "boatProfiles": [],
  "flights": {},
  "pairings": []
}